tons/__init__.py
tons/logging_.py
tons/settings.py
tons/version.py
tons/config/__init__.py
tons/config/_config.py
tons/config/_dns.py
tons/config/_exceptions.py
tons/config/_gui.py
tons/config/_jetton.py
tons/config/_multisig.py
tons/config/_tons.py
tons/config/_provider/__init__.py
tons/config/_provider/_dapp.py
tons/tonclient/__init__.py
tons/tonclient/_exceptions.py
tons/tonclient/_client/__init__.py
tons/tonclient/_client/_base.py
tons/tonclient/_client/_dapp/__init__.py
tons/tonclient/_client/_dapp/_daemon.py
tons/tonclient/_client/_dapp/_dapp.py
tons/tonclient/_client/_dapp/_queries.py
tons/tonclient/utils/__init__.py
tons/tonclient/utils/_exceptions.py
tons/tonclient/utils/_multisig.py
tons/tonclient/utils/_whitelist.py
tons/tonclient/utils/_keystores/__init__.py
tons/tonclient/utils/_keystores/_backup.py
tons/tonclient/utils/_keystores/_crypto.py
tons/tonclient/utils/_keystores/_record.py
tons/tonclient/utils/_keystores/_keystore/__init__.py
tons/tonclient/utils/_keystores/_keystore/_base.py
tons/tonclient/utils/_keystores/_keystore/_password.py
tons/tonclient/utils/_keystores/_keystore/_secret.py
tons/tonclient/utils/_keystores/_keystore/_yubikey.py
tons/tonclient/utils/_tonconnect/__init__.py
tons/tonclient/utils/_tonconnect/_handlers.py
tons/tonclient/utils/_tonconnect/_models.py
tons/tonclient/utils/_tonconnect/_utils.py
tons/tonsdk/__init__.py
tons/tonsdk/_exceptions.py
tons/tonsdk/boc/__init__.py
tons/tonsdk/boc/_bit_string.py
tons/tonsdk/boc/_builder.py
tons/tonsdk/boc/_cell.py
tons/tonsdk/boc/_dict_builder.py
tons/tonsdk/boc/_message_relaxed.py
tons/tonsdk/boc/_slice.py
tons/tonsdk/boc/dict/__init__.py
tons/tonsdk/boc/dict/deserialize_dict.py
tons/tonsdk/boc/dict/find_common_prefix.py
tons/tonsdk/boc/dict/serialize_dict.py
tons/tonsdk/contract/__init__.py
tons/tonsdk/contract/token/__init__.py
tons/tonsdk/contract/token/ft/__init__.py
tons/tonsdk/contract/token/ft/jetton_minter.py
tons/tonsdk/contract/token/ft/jetton_wallet.py
tons-1.6.5.dist-info/LICENSE
tons-1.6.5.dist-info/METADATA
tons-1.6.5.dist-info/WHEEL
tons-1.6.5.dist-info/entry_points.txt
tons-1.6.5.dist-info/top_level.txt
tons-1.6.5.dist-info/RECORD
