Metadata-Version: 2.2
Name: tons
Version: 1.6.5
Summary: TON Stash - secure TON wallet
Author: tonfactory.org
Keywords: TON,wallet,TON wallet,blockchain,security,safety,cryptowallet,crypto
Classifier: Programming Language :: Python :: 3
Classifier: Environment :: Console
Classifier: Environment :: Other Environment
Classifier: Environment :: Web Environment
Classifier: Intended Audience :: Developers
Classifier: Intended Audience :: Financial and Insurance Industry
Classifier: Intended Audience :: End Users/Desktop
Classifier: License :: OSI Approved :: GNU General Public License v3 (GPLv3)
Classifier: Natural Language :: English
Classifier: Operating System :: OS Independent
Classifier: Programming Language :: Python
Classifier: Programming Language :: Python :: 3
Classifier: Programming Language :: Python :: 3.8
Classifier: Programming Language :: Python :: 3.9
Classifier: Programming Language :: Python :: 3.10
Classifier: Programming Language :: Python :: 3.11
Classifier: Programming Language :: Python :: 3 :: Only
Classifier: Topic :: Adaptive Technologies
Classifier: Topic :: Office/Business :: Financial
Requires-Python: >=3.8
License-File: LICENSE
Requires-Dist: appdirs==1.4.4
Requires-Dist: aiohttp==3.9.2
Requires-Dist: bitarray>=2.7.6
Requires-Dist: certifi>=2017.4.17
Requires-Dist: cffi==1.15.1
Requires-Dist: click==8.1.4
Requires-Dist: colorama==0.4.6
Requires-Dist: cryptography==42.0.4
Requires-Dist: fe25519==1.4.2
Requires-Dist: ge25519==1.4.3
Requires-Dist: graphql_query==1.1.1
Requires-Dist: inquirer==3.1.3
Requires-Dist: prettytable==3.8.0
Requires-Dist: pycparser==2.21
Requires-Dist: pydantic==1.10.11
Requires-Dist: pynacl==1.5.0
Requires-Dist: pyqt6==6.5.2
Requires-Dist: PyQt6-Qt6==6.5.2
Requires-Dist: python-dateutil==2.8.2
Requires-Dist: pyyaml==6.0
Requires-Dist: readchar~=4.0.5
Requires-Dist: requests==2.31.0
Requires-Dist: tvm-valuetypes==0.0.10
Requires-Dist: typing_extensions==4.7.1
Requires-Dist: gql[requests]==3.4.1
Requires-Dist: yubikey-manager==5.1.1
Requires-Dist: websockets==11.0.3
Requires-Dist: qrcode~=7.4.2
Requires-Dist: Pillow~=10.0.1
Requires-Dist: notify-py~=0.3.42
Requires-Dist: pyobjc-core==10.0; platform_system == "Darwin"
Requires-Dist: pyobjc-framework-Cocoa==10.0; platform_system == "Darwin"
